ocpp_serverless/__init__.py
ocpp_serverless-0.0.1.dist-info/WHEEL
ocpp_serverless-0.0.1.dist-info/METADATA
ocpp_serverless-0.0.1.dist-info/RECORD
